[
  {
    "_peopleID": "5790402b-5faf-4990-8938-a8b38422e9f0",
    "_name": "Luis",
    "_cpf": "32873298768",
    "_isActive": false,
    "_bankManagerID": "5790402b-5faf-4990-8938-a8b38422e9f0",
    " _currentAccount": [],
    " _poupancaAccount": []
  },
  {
    "_peopleID": "80ca9aae-5188-4fb0-ab24-8fd7758af571",
    "_name": "Mariana",
    "_cpf": "76523498765",
    "_isActive": true,
    "_currentAccount": [],
    "_poupancaAccount": []
  },
  {
    "_peopleID": "62ea1c1f-2d58-4c99-9d7b-06195cfb2e40",
    "_name": "John Doe",
    "_cpf": "34567912345",
    "_isActive": true,
    "_currentAccount": [],
    "_poupancaAccount": []
  },
  {
    "_peopleID": "af2dfa64-f3d1-4d44-91d0-329b5ad1efee",
    "_name": "John Doe",
    "_cpf": "34567912345",
    "_isActive": true,
    "_currentAccount": [],
    "_poupancaAccount": []
  }
]